ringcentral_chatbot_factory/__init__.py
ringcentral_chatbot_factory/cmd.py
ringcentral_chatbot_factory/rcf.py
temp/__init__.py
temp/ff.py
temp/core/__init__.py
temp/core/bot.py
temp/core/bot_oauth.py
temp/core/bot_webhook.py
temp/core/common.py
temp/core/config.py
temp/core/config_default.py
temp/core/data.py
temp/core/db.py
temp/core/dynamodb.py
temp/core/filedb.py
temp/core/route.py
temp/core/user.py
temp/core/user_oauth.py
temp/core/user_webhook.py
ringcentral_chatbot_factory-0.1.2.dist-info/METADATA
ringcentral_chatbot_factory-0.1.2.dist-info/WHEEL
ringcentral_chatbot_factory-0.1.2.dist-info/entry_points.txt
ringcentral_chatbot_factory-0.1.2.dist-info/top_level.txt
ringcentral_chatbot_factory-0.1.2.dist-info/RECORD
