Metadata-Version: 2.1
Name: ringcentral-chatbot-factory
Version: 0.1.2
Summary: Cli tool to generate RingCentral chatbot project
Home-page: https://github.com/ringcentral/ringcentral-chatbot-factory-py
Author: Drake Zhao
Author-email: drake.zhao@ringcentral.com
License: UNKNOWN
Keywords: ringcentral,bot,framework
Platform: UNKNOWN
Classifier: Programming Language :: Python :: 3
Classifier: License :: OSI Approved :: MIT License
Classifier: Operating System :: OS Independent
Requires-Dist: requests-download
Requires-Dist: pydash
Requires-Dist: PyInquirer
